[
  {
    "name": "Advance 1",
    "description": "Moves forward by 1 tile.",
    "priority": 1,
    "cost": 5,
    "actions": [
      {
        "type": "MOVEMENT",
        "targetSelf": true,
        "value": 1
      }
    ]
  },
  {
    "name": "Advance 2",
    "description": "Moves forward by 2 tiles.",
    "priority": 2,
    "cost": 7,
    "actions": [
      {
        "type": "MOVEMENT",
        "targetSelf": true,
        "value": 2
      }
    ]
  },
  {
    "name": "Advance 3",
    "description": "Moves forward by 3 tiles.",
    "priority": 3,
    "cost": 10,
    "actions": [
      {
        "type": "MOVEMENT",
        "targetSelf": true,
        "value": 3
      }
    ]
  },
  {
    "name": "Retreat 1",
    "description": "Moves backward by 1 tile.",
    "priority": 2,
    "cost": 5,
    "actions": [
      {
        "type": "MOVEMENT",
        "targetSelf": true,
        "value": -1
      }
    ]
  },
  {
    "name": "Retreat 2",
    "description": "Moves backward by 2 tiles.",
    "priority": 3,
    "cost": 7,
    "actions": [
      {
        "type": "MOVEMENT",
        "targetSelf": true,
        "value": -2
      }
    ]
  },
  {
    "name": "Retreat 3",
    "description": "Moves backward by 3 tiles.",
    "priority": 4,
    "cost": 10,
    "actions": [
      {
        "type": "MOVEMENT",
        "targetSelf": true,
        "value": -3
      }
    ]
  },
  {
    "name": "Simple attack",
    "description": "A simple attack for 50% damage.",
    "priority": 5,
    "cost": 10,
    "actions": [
      {
        "type": "ATTACK",
        "attackType": 0,
        "default": 50,
        "modifiers": []
      }
    ]
  },
  {
    "name": "Care",
    "description": "Recover 10 health point,",
    "priority": 5,
    "cost": 10,
    "actions": [
      {
        "type": "HEAL",
        "healType": 0,
        "value": 10
      }
    ]
  },
  {
    "name": "Undo",
    "description": "Undo the last action of your opponent.",
    "priority": 2,
    "cost": 15,
    "actions": [
      {
        "type": "UNDO",
        "targetSelf": false
      }
    ]
  }
]